README.rst
setup.py
apispec_chalice/__init__.py
apispec_chalice/chalice.py
apispec_chalice.egg-info/PKG-INFO
apispec_chalice.egg-info/SOURCES.txt
apispec_chalice.egg-info/dependency_links.txt
apispec_chalice.egg-info/requires.txt
apispec_chalice.egg-info/top_level.txt