Metadata-Version: 1.0
Name: apispec-chalice
Version: 0.2.1
Summary: Chalice plugin for the apispec library
Home-page: UNKNOWN
Author: Mathew Marcus
Author-email: mathewmarcus456@gmail.com
License: UNKNOWN
Platform: UNKNOWN
